heisenberg_cli/__init__.py
heisenberg_cli/__main__.py
heisenberg_cli/command/__init__.py
heisenberg_cli/command/base.py
heisenberg_cli/command/code_inspect.py
heisenberg_cli/command/job_status.py
heisenberg_cli/command/setup_project.py
heisenberg_cli/command/submit_to_network.py
heisenberg_cli/exceptions.py
heisenberg_cli/models.py
heisenberg_cli/template/README.md-tmpl
heisenberg_cli/template/config.py-tmpl
heisenberg_cli/template/env-templ
heisenberg_cli/template/jobignore-tmpl
heisenberg_cli/template/pyproject._toml-tmpl
heisenberg_cli/template/recommender-jupyter.ipynb-tmpl
heisenberg_cli/template/recommender.py-tmpl
heisenberg_cli/utils/__init__.py
heisenberg_cli/utils/binary_utils.py
heisenberg_cli/utils/date_utils.py
heisenberg_cli/utils/feature_extractor.py
heisenberg_cli/utils/file.py
heisenberg_cli/utils/file_cryptography.py
heisenberg_cli/utils/jobignore.py
heisenberg_cli/utils/logging/__init__.py
heisenberg_cli/utils/logging/base_logger.py
heisenberg_cli/utils/logging/console_logger.py
heisenberg_cli/utils/logging/logstash_logger.py
heisenberg_cli/utils/logging/multi_logger.py
heisenberg_cli/utils/obfuscate.py
heisenberg_cli/utils/package_utils.py
heisenberg_cli/utils/rest.py
heisenberg_cli/utils/zip_utils.py
heisenberg_cli-1.1.4.dist-info/METADATA
heisenberg_cli-1.1.4.dist-info/WHEEL
heisenberg_cli-1.1.4.dist-info/entry_points.txt
heisenberg_cli-1.1.4.dist-info/RECORD
