Metadata-Version: 2.3
Name: heisenberg-cli
Version: 1.1.4
Summary: Heisenberg CLI - Command line interface for using Heisenberg services
License: Commercial - see LICENSE.txt
Author: SeshatLabs
Author-email: info@seshatlabs.xyz
Requires-Python: >=3.11,<4.0
Classifier: License :: Other/Proprietary License
Classifier: Programming Language :: Python :: 3
Classifier: Programming Language :: Python :: 3.11
Classifier: Programming Language :: Python :: 3.12
Classifier: Programming Language :: Python :: 3.13
Requires-Dist: backoff (>=2.2.1,<3.0.0)
Requires-Dist: boto3 (>=1.40.51,<2.0.0)
Requires-Dist: croniter (>=6.0.0,<7.0.0)
Requires-Dist: cryptography (>=46.0.2,<47.0.0)
Requires-Dist: loguru (>=0.7.3,<0.8.0)
Requires-Dist: pyarmor (>=9.1.9,<10.0.0)
Requires-Dist: python-dotenv (>=1.0.0,<2.0.0)
Requires-Dist: requests (>=2.32.5,<3.0.0)
Requires-Dist: rich (>=14.2.0,<15.0.0)
Requires-Dist: toml (>=0.10.2,<0.11.0)
Requires-Dist: typer (>=0.19.2,<0.20.0)
